{
	"pages": [ //pages数组中第一项表示应用启动页，参考：https://uniapp.dcloud.io/collocation/pages
		{
			"path": "pages/index/index",
			"style": {
				"navigationBarTitleText": "海报生成器"
			}
		},
		{
			"path": "pages/static-painter/index",
			"style": {
				"navigationBarTitleText": "静态海报",
				"usingComponents": {
					"painter": "/wxcomponents/painter/painter"
				}
			}
		}, {
			"path": "pages/dance-painter/index",
			"style": {
				"navigationBarTitleText": "海报编辑器",
				"usingComponents": {
					"painter": "/wxcomponents/painter/painter"
				}
			}

		}
	],
	"globalStyle": {
		"navigationBarTextStyle": "black",
		"navigationBarTitleText": "uni-app",
		"navigationBarBackgroundColor": "#F8F8F8",
		"backgroundColor": "#F8F8F8"
	}
}
